pykis/__env__.py
pykis/__init__.py
pykis/exceptions.py
pykis/kis.py
pykis/logging.py
pykis/types.py
pykis/adapter/account/balance.py
pykis/adapter/account/order.py
pykis/adapter/account_product/order.py
pykis/adapter/account_product/order_modify.py
pykis/adapter/product/quote.py
pykis/adapter/websocket/execution.py
pykis/adapter/websocket/price.py
pykis/api/account/balance.py
pykis/api/account/daily_order.py
pykis/api/account/order.py
pykis/api/account/order_modify.py
pykis/api/account/order_profit.py
pykis/api/account/orderable_amount.py
pykis/api/account/pending_order.py
pykis/api/auth/token.py
pykis/api/auth/websocket.py
pykis/api/base/account.py
pykis/api/base/account_product.py
pykis/api/base/market.py
pykis/api/base/product.py
pykis/api/stock/chart.py
pykis/api/stock/daily_chart.py
pykis/api/stock/day_chart.py
pykis/api/stock/info.py
pykis/api/stock/market.py
pykis/api/stock/order_book.py
pykis/api/stock/quote.py
pykis/api/stock/trading_hours.py
pykis/api/websocket/__init__.py
pykis/api/websocket/order_book.py
pykis/api/websocket/order_execution.py
pykis/api/websocket/price.py
pykis/client/account.py
pykis/client/appkey.py
pykis/client/auth.py
pykis/client/cache.py
pykis/client/exceptions.py
pykis/client/form.py
pykis/client/messaging.py
pykis/client/object.py
pykis/client/page.py
pykis/client/websocket.py
pykis/event/__init__.py
pykis/event/handler.py
pykis/event/subscription.py
pykis/event/filters/__init__.py
pykis/event/filters/order.py
pykis/event/filters/product.py
pykis/event/filters/subscription.py
pykis/responses/dynamic.py
pykis/responses/exceptions.py
pykis/responses/response.py
pykis/responses/types.py
pykis/responses/websocket.py
pykis/scope/__init__.py
pykis/scope/account.py
pykis/scope/base.py
pykis/scope/stock.py
pykis/utils/diagnosis.py
pykis/utils/math.py
pykis/utils/rate_limit.py
pykis/utils/reference.py
pykis/utils/repr.py
pykis/utils/thread_safe.py
pykis/utils/timex.py
pykis/utils/timezone.py
pykis/utils/typing.py
pykis/utils/workspace.py
python_kis-2.1.6.dist-info/licenses/LICENCE
python_kis-2.1.6.dist-info/METADATA
python_kis-2.1.6.dist-info/WHEEL
python_kis-2.1.6.dist-info/top_level.txt
python_kis-2.1.6.dist-info/RECORD
