Metadata-Version: 2.4
Name: python-kis
Version: 2.1.6
Summary: 파이썬 한국투자증권 REST 기반 Trading API 라이브러리
Author-email: Soju06 <qlskssk@gmail.com>
License: MIT
Project-URL: Bug Tracker, https://github.com/Soju06/python-kis/issues
Project-URL: Documentation, https://github.com/Soju06/python-kis/wiki/Tutorial
Project-URL: Source Code, https://github.com/Soju06/python-kis
Keywords: python,client,library,trading,websocket,realtime,investing,korean,investment,autotrading,koreainvestment
Classifier: Intended Audience :: Developers
Classifier: Intended Audience :: Education
Classifier: Intended Audience :: Information Technology
Classifier: Intended Audience :: Financial and Insurance Industry
Classifier: License :: OSI Approved :: MIT License
Classifier: Programming Language :: Python :: 3
Classifier: Programming Language :: Python :: 3.10
Classifier: Programming Language :: Python :: 3.11
Classifier: Programming Language :: Python :: 3.12
Classifier: Programming Language :: Python :: 3.13
Classifier: Topic :: Software Development :: Libraries
Classifier: Topic :: Software Development :: Libraries :: Python Modules
Classifier: Topic :: Office/Business :: Financial
Classifier: Topic :: Office/Business :: Financial :: Investment
Classifier: Typing :: Typed
Requires-Python: >=3.10
License-File: LICENCE
Requires-Dist: requests>=2.32.3
Requires-Dist: websocket-client>=1.8.0
Requires-Dist: cryptography>=43.0.0
Requires-Dist: colorlog>=6.8.2
Dynamic: license-file
